{
  "_links": {
    "html": {
      "href": "https://github.com/opensciencegrid/htcondor-ce/pull/153#pullrequestreview-49565485"
    }, 
    "pull_request": {
      "href": "https://api.github.com/repos/opensciencegrid/htcondor-ce/pulls/153"
    }
  }, 
  "author_association": "OWNER", 
  "body": "Much better!  Thanks for tracking down the upstream HTCondor bug too.\r\n\r\nJust one question embedded for @brianhlin that might require changes.  Other than that, it looks ready to go.", 
  "commit_id": "29ee0efcecf08fc65b496e1881f838c8d518373f", 
  "html_url": "https://github.com/opensciencegrid/htcondor-ce/pull/153#pullrequestreview-49565485", 
  "id": 49565485, 
  "pull_request_url": "https://api.github.com/repos/opensciencegrid/htcondor-ce/pulls/153", 
  "state": "CHANGES_REQUESTED", 
  "submitted_at": "2017-07-12T17:43:54Z", 
  "user": {
    "avatar_url": "https://avatars2.githubusercontent.com/u/1093447?v=4", 
    "events_url": "https://api.github.com/users/bbockelm/events{/privacy}", 
    "followers_url": "https://api.github.com/users/bbockelm/followers", 
    "following_url": "https://api.github.com/users/bbockelm/following{/other_user}", 
    "gists_url": "https://api.github.com/users/bbockelm/gists{/gist_id}", 
    "gravatar_id": "", 
    "html_url": "https://github.com/bbockelm", 
    "id": 1093447, 
    "login": "bbockelm", 
    "organizations_url": "https://api.github.com/users/bbockelm/orgs", 
    "received_events_url": "https://api.github.com/users/bbockelm/received_events", 
    "repos_url": "https://api.github.com/users/bbockelm/repos", 
    "site_admin": false, 
    "starred_url": "https://api.github.com/users/bbockelm/starred{/owner}{/repo}", 
    "subscriptions_url": "https://api.github.com/users/bbockelm/subscriptions", 
    "type": "User", 
    "url": "https://api.github.com/users/bbockelm"
  }
}
