{
  "_links": {
    "html": {
      "href": "https://github.com/opensciencegrid/docs/pull/160#discussion_r138943426"
    }, 
    "pull_request": {
      "href": "https://api.github.com/repos/opensciencegrid/docs/pulls/160"
    }, 
    "self": {
      "href": "https://api.github.com/repos/opensciencegrid/docs/pulls/comments/138943426"
    }
  }, 
  "author_association": "OWNER", 
  "body": "Could you take everything from this line up until the reference section, convert it, and add it to the troubleshooting section of the RSV doc [here](https://opensciencegrid.github.io/docs/monitoring/install-rsv/#troubleshooting-rsv)? Don't forget the contents of the `%INCLUDE`", 
  "commit_id": "f18cfa294375fb12561589f54b8d380d37262cb2", 
  "created_at": "2017-09-14T16:24:06Z", 
  "diff_hunk": "@@ -0,0 +1,110 @@\n+---+!! !RSV Troubleshooting Guide\n+%DOC_STATUS_TABLE%\n+%TOC%\n+\n+---+ About this Document\n+This document describes  how to troubleshoot !RSV v3 (part of OSG 3.0).\n+\n+---+ How to get Help?\n+To get assistance please use [[HelpProcedure][Help Procedure]].\n+The developers of a specific metric/probe may provide additional support channel, please check the specific troubleshooting document if your metric is listed in the table below.\n+\n+%INCLUDE{\"RsvControl\" section=\"RsvProfilerNT\"}%", 
  "html_url": "https://github.com/opensciencegrid/docs/pull/160#discussion_r138943426", 
  "id": 138943426, 
  "original_commit_id": "cfd7fdf83988157dae9a47d65d241327f6a7145d", 
  "original_position": 12, 
  "path": "archive/TroubleshootRsv", 
  "position": 12, 
  "pull_request_review_id": 62808432, 
  "pull_request_url": "https://api.github.com/repos/opensciencegrid/docs/pulls/160", 
  "updated_at": "2017-10-12T21:39:50Z", 
  "url": "https://api.github.com/repos/opensciencegrid/docs/pulls/comments/138943426", 
  "user": {
    "avatar_url": "https://avatars3.githubusercontent.com/u/390105?v=4", 
    "events_url": "https://api.github.com/users/brianhlin/events{/privacy}", 
    "followers_url": "https://api.github.com/users/brianhlin/followers", 
    "following_url": "https://api.github.com/users/brianhlin/following{/other_user}", 
    "gists_url": "https://api.github.com/users/brianhlin/gists{/gist_id}", 
    "gravatar_id": "", 
    "html_url": "https://github.com/brianhlin", 
    "id": 390105, 
    "login": "brianhlin", 
    "organizations_url": "https://api.github.com/users/brianhlin/orgs", 
    "received_events_url": "https://api.github.com/users/brianhlin/received_events", 
    "repos_url": "https://api.github.com/users/brianhlin/repos", 
    "site_admin": false, 
    "starred_url": "https://api.github.com/users/brianhlin/starred{/owner}{/repo}", 
    "subscriptions_url": "https://api.github.com/users/brianhlin/subscriptions", 
    "type": "User", 
    "url": "https://api.github.com/users/brianhlin"
  }
}
