{
  "author_association": "CONTRIBUTOR", 
  "body": "Am I better off rebasing and submitting my PR to `opensciencegrid:master`?", 
  "created_at": "2017-11-13T19:37:07Z", 
  "html_url": "https://github.com/opensciencegrid/cvmfs-config-osg/pull/3#issuecomment-344032903", 
  "id": 344032903, 
  "issue_url": "https://api.github.com/repos/opensciencegrid/cvmfs-config-osg/issues/3", 
  "updated_at": "2017-11-13T19:37:07Z", 
  "url": "https://api.github.com/repos/opensciencegrid/cvmfs-config-osg/issues/comments/344032903", 
  "user": {
    "avatar_url": "https://avatars1.githubusercontent.com/u/7475598?v=4", 
    "events_url": "https://api.github.com/users/tpdownes/events{/privacy}", 
    "followers_url": "https://api.github.com/users/tpdownes/followers", 
    "following_url": "https://api.github.com/users/tpdownes/following{/other_user}", 
    "gists_url": "https://api.github.com/users/tpdownes/gists{/gist_id}", 
    "gravatar_id": "", 
    "html_url": "https://github.com/tpdownes", 
    "id": 7475598, 
    "login": "tpdownes", 
    "organizations_url": "https://api.github.com/users/tpdownes/orgs", 
    "received_events_url": "https://api.github.com/users/tpdownes/received_events", 
    "repos_url": "https://api.github.com/users/tpdownes/repos", 
    "site_admin": false, 
    "starred_url": "https://api.github.com/users/tpdownes/starred{/owner}{/repo}", 
    "subscriptions_url": "https://api.github.com/users/tpdownes/subscriptions", 
    "type": "User", 
    "url": "https://api.github.com/users/tpdownes"
  }
}
